argparse_deco/__init__.py
argparse_deco/arguments.py
argparse_deco/cli.py
argparse_deco/command.py
argparse_deco/compat.py
argparse_deco/runner.py
argparse_deco/version.py
argparse_deco-0.6.0.dist-info/COPYING
argparse_deco-0.6.0.dist-info/METADATA
argparse_deco-0.6.0.dist-info/WHEEL
argparse_deco-0.6.0.dist-info/top_level.txt
argparse_deco-0.6.0.dist-info/RECORD
